[
  {
    "ID": 1,
    "Champname": "Annie"
  },
  {
    "ID": 2,
    "Champname": "Olaf"
  },
  {
    "ID": 3,
    "Champname": "Galio"
  },
  {
    "ID": 4,
    "Champname": "Twisted Fate"
  },
  {
    "ID": 5,
    "Champname": "Xin Zhao"
  },
  {
    "ID": 6,
    "Champname": "Urgot"
  },
  {
    "ID": 7,
    "Champname": "Leblanc"
  },
  {
    "ID": 8,
    "Champname": "Vladimir"
  },
  {
    "ID": 9,
    "Champname": "Fiddlesticks"
  },
  {
    "ID": 10,
    "Champname": "Kayle"
  },
  {
    "ID": 11,
    "Champname": "Master Yi"
  },
  {
    "ID": 12,
    "Champname": "Alistar"
  },
  {
    "ID": 13,
    "Champname": "Ryze"
  },
  {
    "ID": 14,
    "Champname": "Sion"
  },
  {
    "ID": 15,
    "Champname": "Sivir"
  },
  {
    "ID": 16,
    "Champname": "Soraka"
  },
  {
    "ID": 17,
    "Champname": "Teemo"
  },
  {
    "ID": 18,
    "Champname": "Tristana"
  },
  {
    "ID": 19,
    "Champname": "Warwick"
  },
  {
    "ID": 20,
    "Champname": "Nunu"
  },
  {
    "ID": 21,
    "Champname": "Miss Fortune"
  },
  {
    "ID": 22,
    "Champname": "Ashe"
  },
  {
    "ID": 23,
    "Champname": "Tryndamere"
  },
  {
    "ID": 24,
    "Champname": "Jax"
  },
  {
    "ID": 25,
    "Champname": "Morgana"
  },
  {
    "ID": 26,
    "Champname": "Zilean"
  },
  {
    "ID": 27,
    "Champname": "Singed"
  },
  {
    "ID": 28,
    "Champname": "Evelynn"
  },
  {
    "ID": 29,
    "Champname": "Twitch"
  },
  {
    "ID": 30,
    "Champname": "Karthus"
  },
  {
    "ID": 31,
    "Champname": "Cho'Gath"
  },
  {
    "ID": 32,
    "Champname": "Amumu"
  },
  {
    "ID": 33,
    "Champname": "Rammus"
  },
  {
    "ID": 34,
    "Champname": "Anivia"
  },
  {
    "ID": 35,
    "Champname": "Shaco"
  },
  {
    "ID": 36,
    "Champname": "Dr. Mundo"
  },
  {
    "ID": 37,
    "Champname": "Sona"
  },
  {
    "ID": 38,
    "Champname": "Kassadin"
  },
  {
    "ID": 39,
    "Champname": "Irelia"
  },
  {
    "ID": 40,
    "Champname": "Janna"
  },
  {
    "ID": 41,
    "Champname": "Gangplank"
  },
  {
    "ID": 42,
    "Champname": "Corki"
  },
  {
    "ID": 43,
    "Champname": "Karma"
  },
  {
    "ID": 44,
    "Champname": "Taric"
  },
  {
    "ID": 45,
    "Champname": "Veigar"
  },
  {
    "ID": 48,
    "Champname": "Trundle"
  },
  {
    "ID": 50,
    "Champname": "Swain"
  },
  {
    "ID": 51,
    "Champname": "Caitlyn"
  },
  {
    "ID": 53,
    "Champname": "Blitzcrank"
  },
  {
    "ID": 54,
    "Champname": "Malphite"
  },
  {
    "ID": 55,
    "Champname": "Katarina"
  },
  {
    "ID": 56,
    "Champname": "Nocturne"
  },
  {
    "ID": 57,
    "Champname": "Maokai"
  },
  {
    "ID": 58,
    "Champname": "Renekton"
  },
  {
    "ID": 59,
    "Champname": "Jarvan IV"
  },
  {
    "ID": 60,
    "Champname": "Elise"
  },
  {
    "ID": 61,
    "Champname": "Orianna"
  },
  {
    "ID": 62,
    "Champname": "Wukong"
  },
  {
    "ID": 63,
    "Champname": "Brand"
  },
  {
    "ID": 64,
    "Champname": "Lee Sin"
  },
  {
    "ID": 67,
    "Champname": "Vayne"
  },
  {
    "ID": 68,
    "Champname": "Rumble"
  },
  {
    "ID": 69,
    "Champname": "Cassiopeia"
  },
  {
    "ID": 72,
    "Champname": "Skarner"
  },
  {
    "ID": 74,
    "Champname": "Heimerdinger"
  },
  {
    "ID": 75,
    "Champname": "Nasus"
  },
  {
    "ID": 76,
    "Champname": "Nidalee"
  },
  {
    "ID": 77,
    "Champname": "Udyr"
  },
  {
    "ID": 78,
    "Champname": "Poppy"
  },
  {
    "ID": 79,
    "Champname": "Gragas"
  },
  {
    "ID": 80,
    "Champname": "Pantheon"
  },
  {
    "ID": 81,
    "Champname": "Ezreal"
  },
  {
    "ID": 82,
    "Champname": "Mordekaiser"
  },
  {
    "ID": 83,
    "Champname": "Yorick"
  },
  {
    "ID": 84,
    "Champname": "Akali"
  },
  {
    "ID": 85,
    "Champname": "Kennen"
  },
  {
    "ID": 86,
    "Champname": "Garen"
  },
  {
    "ID": 89,
    "Champname": "Leona"
  },
  {
    "ID": 90,
    "Champname": "Malzahar"
  },
  {
    "ID": 91,
    "Champname": "Talon"
  },
  {
    "ID": 92,
    "Champname": "Riven"
  },
  {
    "ID": 96,
    "Champname": "Kog'Maw"
  },
  {
    "ID": 98,
    "Champname": "Shen"
  },
  {
    "ID": 99,
    "Champname": "Lux"
  },
  {
    "ID": 101,
    "Champname": "Xerath"
  },
  {
    "ID": 102,
    "Champname": "Shyvana"
  },
  {
    "ID": 103,
    "Champname": "Ahri"
  },
  {
    "ID": 104,
    "Champname": "Graves"
  },
  {
    "ID": 105,
    "Champname": "Fizz"
  },
  {
    "ID": 106,
    "Champname": "Volibear"
  },
  {
    "ID": 107,
    "Champname": "Rengar"
  },
  {
    "ID": 110,
    "Champname": "Varus"
  },
  {
    "ID": 111,
    "Champname": "Nautilus"
  },
  {
    "ID": 112,
    "Champname": "Viktor"
  },
  {
    "ID": 113,
    "Champname": "Sejuani"
  },
  {
    "ID": 114,
    "Champname": "Fiora"
  },
  {
    "ID": 115,
    "Champname": "Ziggs"
  },
  {
    "ID": 117,
    "Champname": "Lulu"
  },
  {
    "ID": 119,
    "Champname": "Draven"
  },
  {
    "ID": 120,
    "Champname": "Hecarim"
  },
  {
    "ID": 121,
    "Champname": "Kha'Zix"
  },
  {
    "ID": 122,
    "Champname": "Darius"
  },
  {
    "ID": 126,
    "Champname": "Jayce"
  },
  {
    "ID": 127,
    "Champname": "Lissandra"
  },
  {
    "ID": 131,
    "Champname": "Diana"
  },
  {
    "ID": 133,
    "Champname": "Quinn"
  },
  {
    "ID": 134,
    "Champname": "Syndra"
  },
  {
    "ID": 136,
    "Champname": "Aurelion Sol"
  },
  {
    "ID": 141,
    "Champname": "Kayn"
  },
    {
    "ID": 142,
    "Champname": "Zoe"
  },
  {
    "ID": 143,
    "Champname": "Zyra"
  },
  {
    "ID": 145,
    "Champname": "Kai'Sa"
  },
  {
    "ID": 150,
    "Champname": "Gnar"
  },
  {
    "ID": 154,
    "Champname": "Zac"
  },
  {
    "ID": 157,
    "Champname": "Yasuo"
  },
  {
    "ID": 161,
    "Champname": "Velkoz"
  },
  {
    "ID": 163,
    "Champname": "Taliyah"
  },
  {
    "ID": 164,
    "Champname": "Camille"
  },
  {
    "ID": 201,
    "Champname": "Braum"
  },
  {
    "ID": 202,
    "Champname": "Jhin"
  },
  {
    "ID": 203,
    "Champname": "Kindred"
  },
  {
    "ID": 222,
    "Champname": "Jinx"
  },
  {
    "ID": 223,
    "Champname": "Tahm Kench"
  },
  {
    "ID": 236,
    "Champname": "Lucian"
  },
  {
    "ID": 238,
    "Champname": "Zed"
  },
  {
    "ID": 240,
    "Champname": "Kled"
  },
  {
    "ID": 245,
    "Champname": "Ekko"
  },
  {
    "ID": 246,
    "Champname": "Qiyana"
  },
  {
    "ID": 254,
    "Champname": "Vi"
  },
  {
    "ID": 266,
    "Champname": "Aatrox"
  },
  {
    "ID": 267,
    "Champname": "Nami"
  },
  {
    "ID": 268,
    "Champname": "Azir"
  },
  {
    "ID": 350,
    "Champname": "Yuumi"
  },
  {
    "ID": 412,
    "Champname": "Thresh"
  },
  {
    "ID": 420,
    "Champname": "Illaoi"
  },
  {
    "ID": 421,
    "Champname": "Rek'Sai"
  },
  {
    "ID": 427,
    "Champname": "Ivern"
  },
  {
    "ID": 429,
    "Champname": "Kalista"
  },
  {
    "ID": 432,
    "Champname": "Bard"
  },
  {
    "ID": 497,
    "Champname": "Rakan"
  },
  {
    "ID": 498,
    "Champname": "Xayah"
  },
  {
    "ID": 516,
    "Champname": "Ornn"
  },
  {
    "ID": 517,
    "Champname": "Sylas"
  },
  {
    "ID": 518,
    "Champname": "Neeko"
  },
  {
    "ID": 555,
    "Champname": "Pyke"
  },
]
